CHANGES.md
MANIFEST.in
README.md
UNLICENSE
setup.py
src/pyramid_hsts/__init__.py
src/pyramid_hsts.egg-info/PKG-INFO
src/pyramid_hsts.egg-info/SOURCES.txt
src/pyramid_hsts.egg-info/dependency_links.txt
src/pyramid_hsts.egg-info/not-zip-safe
src/pyramid_hsts.egg-info/requires.txt
src/pyramid_hsts.egg-info/top_level.txt