Metadata-Version: 1.0
Name: pyramid-hsts
Version: 1.1.2
Summary: HTTP Strict Transport Security for a Pyramid application.
Home-page: http://github.com/thruflo/pyramid_hsts
Author: James Arthur
Author-email: username: thruflo, domain: gmail.com
License: This is free and unencumbered software released into the public domain.
Platform: UNKNOWN
Classifier: Development Status :: 5 - Production/Stable
Classifier: Environment :: Web Environment
Classifier: Intended Audience :: Developers
Classifier: License :: Public Domain
Classifier: Natural Language :: English
Classifier: Operating System :: OS Independent
Classifier: Programming Language :: Python
Classifier: Programming Language :: Python :: 2.7
Classifier: Programming Language :: Python :: 3
Classifier: Framework :: Pylons
Classifier: Topic :: Internet :: WWW/HTTP
Classifier: Topic :: Internet :: WWW/HTTP :: WSGI
Classifier: Topic :: Software Development :: Libraries :: Python Modules
